{
 "wsj": [
  {
   "img": "i/IDS-Virus.jpg", 
   "title": "Molecule Shows Ability to Block AIDS Virus", 
   "url": "http://www.wsj.com/articles/study-identifies-potential-vaccine-like-protection-against-hiv-1424260802?mod=trending_now_1", 
   "age": 1424291340, 
   "topComment": "While it seems intuitive that blocking a cell's receptor that HIV uses to spread itself, my question would be: \"what else that the cell required that receptor for, would we be blocking?\"", 
   "tag": "popular", 
   "topCommentNum": 142, 
   "numComments": 71
  }
 ]
}